Metadata-Version: 2.1
Name: safescript
Version: 1.0.2
Summary: A Python module for enhancing web application security
Home-page: https://github.com/ishanoshada/safescript
Author: Ishan Oshada
Author-email: ic31908@gmail.com
License: UNKNOWN
Platform: UNKNOWN
Classifier: Programming Language :: Python :: 3
Classifier: License :: OSI Approved :: MIT License
Classifier: Operating System :: OS Independent
